[
  {
    "id": 13,
    "img": "img/like-girl-1.jpg",
    "name": "Mango People T-shirt",
    "color": "red",
    "size": "XII",
    "price": 52,
    "quantity": 1,
    "shipping": "FREE",
    "link": "single-page"
  },
  {
    "id": 14,
    "img": "img/like-girl-2.jpg",
    "name": "Mango People T-shirt",
    "color": "red",
    "size": "XII",
    "price": 52,
    "quantity": 1,
    "shipping": "FREE",
    "link": "single-page"
  },
  {
    "id": 15,
    "img": "img/like-girl-3.jpg",
    "name": "Mango People T-shirt",
    "color": "red",
    "size": "XII",
    "price": 52,
    "quantity": 1,
    "shipping": "FREE",
    "link": "single-page"
  },
  {
    "id": 16,
    "img": "img/like-girl-4.jpg",
    "name": "Mango People T-shirt",
    "color": "red",
    "size": "XII",
    "price": 52,
    "quantity": 1,
    "shipping": "FREE",
    "link": "single-page"
  }
]